fastutils/__init__.py
fastutils/aesutils.py
fastutils/cacheutils.py
fastutils/cipherutils.py
fastutils/dictutils.py
fastutils/fsutils.py
fastutils/funcutils.py
fastutils/hashutils.py
fastutils/httputils.py
fastutils/imageutils.py
fastutils/jsonutils.py
fastutils/listutils.py
fastutils/logutils.py
fastutils/msgpackutils.py
fastutils/nameutils.py
fastutils/numericutils.py
fastutils/pinyinutils.py
fastutils/randomutils.py
fastutils/rsautils.py
fastutils/strutils.py
fastutils/sysutils.py
fastutils/threadutils.py
fastutils/timeutils.py
fastutils/traceutils.py
fastutils/treeutils.py
fastutils/typingutils.py
fastutils-0.43.5.dist-info/licenses/LICENSE
fastutils-0.43.5.dist-info/METADATA
fastutils-0.43.5.dist-info/WHEEL
fastutils-0.43.5.dist-info/top_level.txt
fastutils-0.43.5.dist-info/RECORD
