Metadata-Version: 2.4
Name: fastutils
Version: 0.43.5
Summary: Collection of simple utils.
Author: rRR0VrFP
Maintainer: rRR0VrFP
License: MIT
Keywords: fastutils
Classifier: Development Status :: 5 - Production/Stable
Classifier: Intended Audience :: Developers
Classifier: Topic :: Software Development :: Libraries :: Python Modules
Classifier: License :: OSI Approved :: MIT License
Classifier: Programming Language :: Python :: 3
Classifier: Programming Language :: Python :: 3 :: Only
Requires-Python: >=2.7, !=3.2.*
License-File: LICENSE
Requires-Dist: bizerror
Requires-Dist: pypinyin
Requires-Dist: jsonformatter
Requires-Dist: requests
Requires-Dist: pytz
Requires-Dist: python-dateutil
Requires-Dist: zenutils
Requires-Dist: pycryptodome; python_version == "2.7"
Requires-Dist: pycryptodome; python_version >= "3.3"
Requires-Dist: pycryptodome==3.6.6; python_version == "3.2"
Requires-Dist: Pillow; python_version == "2.7"
Requires-Dist: Pillow; python_version >= "3.8"
Requires-Dist: Pillow==9.5.0; python_version == "3.7"
Requires-Dist: Pillow==8.4.0; python_version == "3.6"
Requires-Dist: Pillow==7.2.0; python_version == "3.5"
Requires-Dist: Pillow==5.4.1; python_version == "3.4"
Requires-Dist: Pillow==4.3.0; python_version == "3.3"
Requires-Dist: Pillow==4.3.0; python_version == "3.2"
Requires-Dist: rsa<4.7; python_version == "2.7"
Requires-Dist: rsa; python_version >= "3.5"
Requires-Dist: rsa<4.7; python_version == "3.4"
Requires-Dist: rsa<=4.0; python_version == "3.3"
Requires-Dist: rsa<=4.3; python_version == "3.2"
Requires-Dist: PyYAML==5.4.1; python_version == "2.7"
Requires-Dist: PyYAML; python_version > "3.4"
Requires-Dist: PyYAML==5.2; python_version == "3.4"
Requires-Dist: PyYAML==3.11; python_version == "3.3"
Requires-Dist: PyYAML==3.11; python_version == "3.2"
Requires-Dist: psutil==5.9.0; python_version == "2.6"
Requires-Dist: psutil; python_version == "2.7"
Requires-Dist: psutil; python_version >= "3.3"
Requires-Dist: psutil==5.4.3; python_version == "3.2"
Requires-Dist: msgpack; python_version == "2.7"
Requires-Dist: msgpack; python_version >= "3.3"
Requires-Dist: msgpack==1.0.3; python_version == "3.2"
Dynamic: author
Dynamic: classifier
Dynamic: description
Dynamic: description-content-type
Dynamic: keywords
Dynamic: license
Dynamic: license-file
Dynamic: maintainer
Dynamic: requires-dist
Dynamic: requires-python
Dynamic: summary
